setup.py
jsonreader/__init__.py
jsonreader/jsonreader.py
jsonreader.egg-info/PKG-INFO
jsonreader.egg-info/SOURCES.txt
jsonreader.egg-info/dependency_links.txt
jsonreader.egg-info/entry_points.txt
jsonreader.egg-info/top_level.txt