Metadata-Version: 1.0
Name: jsonreader
Version: 0.0.1
Summary: a json reader base on wxpython
Home-page: http://www.the5fire.net
Author: the5fire
Author-email: thefivefire@gmail.com
License: UNKNOWN
Platform: UNKNOWN
